src/__init__.py
src/cli.py
export_translations/__init__.py
export_translations/export_translations.py
import_translations/__init__.py
import_translations/import_translations.py
src/util.py
translations_util-0.2.4.dist-info/LICENSE.txt
translations_util-0.2.4.dist-info/METADATA
translations_util-0.2.4.dist-info/WHEEL
translations_util-0.2.4.dist-info/entry_points.txt
translations_util-0.2.4.dist-info/RECORD
